{"updated_at":"2026-04-26T08:11:34Z","stocks":{"MMM":{"company_name":"3M Company","sector":"Industrials","industry":"Conglomerates","current_price":145.99,"ocf_m":2959.0,"fcf_m":1396.0,"ni_ttm_m":2799.0,"debt_m":12556.0,"cash_m":4149.0,"shares_outstanding_m":521.567261,"beta":1.03,"growth_1_5_pct":8.45,"discount_rate_pct":5.89,"method":"ocf"},"AOS":{"company_name":"A. O. Smith Corporation","sector":"Industrials","industry":"Specialty Industrial Machinery","current_price":64.38,"ocf_m":616.8,"fcf_m":546.0,"ni_ttm_m":546.2,"debt_m":155.0,"cash_m":193.2,"shares_outstanding_m":112.376652,"beta":1.29,"growth_1_5_pct":5.58,"discount_rate_pct":7.0,"method":"ocf"},"ABT":{"company_name":"Abbott Laboratories","sector":"Healthcare","industry":"Medical Devices","current_price":91.13,"ocf_m":9566.0,"fcf_m":7395.0,"ni_ttm_m":6524.0,"debt_m":12929.0,"cash_m":8939.0,"shares_outstanding_m":1737.674869,"beta":0.69,"growth_1_5_pct":9.47,"discount_rate_pct":5.15,"method":"ocf"},"ABBV":{"company_name":"AbbVie Inc.","sector":"Healthcare","industry":"Drug Manufacturers - General","current_price":198.71,"ocf_m":19030.0,"fcf_m":17816.0,"ni_ttm_m":4233.0,"debt_m":67496.0,"cash_m":5257.0,"shares_outstanding_m":1768.762377,"beta":0.29,"growth_1_5_pct":21.32,"discount_rate_pct":5.15,"method":"fcf"},"ACN":{"company_name":"Accenture plc","sector":"Technology","industry":"Information Technology Services","current_price":178.36,"ocf_m":13080.248,"fcf_m":10874.36,"ni_ttm_m":7795.053,"debt_m":5144.385,"cash_m":9405.596,"shares_outstanding_m":613.939268,"beta":1.11,"growth_1_5_pct":7.92,"discount_rate_pct":6.26,"method":"fcf"}}}